CONTRIBUTING.rst
HISTORY.rst
LICENSE
MANIFEST.in
README.rst
setup.cfg
setup.py
docs/Makefile
docs/conf.py
docs/contributing.rst
docs/history.rst
docs/index.rst
docs/installation.rst
docs/make.bat
docs/readme.rst
docs/usage.rst
tests/test_yacm.py
tests/configs/no_rwdb.yml
tests/configs/simple.yml
yacm/__init__.py
yacm.egg-info/PKG-INFO
yacm.egg-info/SOURCES.txt
yacm.egg-info/dependency_links.txt
yacm.egg-info/entry_points.txt
yacm.egg-info/not-zip-safe
yacm.egg-info/requires.txt
yacm.egg-info/top_level.txt