Metadata-Version: 1.1
Name: yacm
Version: 0.1.0
Summary: yet another config module
Home-page: https://github.com/FlorianLudwig/yacm
Author: Florian Ludwig
Author-email: f.ludwig@greyrook.com
License: Apache Software License 2.0
Keywords: yacm
Platform: UNKNOWN
Classifier: Development Status :: 2 - Pre-Alpha
Classifier: Intended Audience :: Developers
Classifier: License :: OSI Approved :: Apache Software License
Classifier: Natural Language :: English
Classifier: Programming Language :: Python :: 3
Classifier: Programming Language :: Python :: 3.5
Classifier: Programming Language :: Python :: 3.6
